account/__init__.py
account/admin.py
account/auth_backends.py
account/compat.py
account/conf.py
account/context_processors.py
account/decorators.py
account/fields.py
account/forms.py
account/hooks.py
account/languages.py
account/managers.py
account/middleware.py
account/mixins.py
account/models.py
account/signals.py
account/timezones.py
account/urls.py
account/utils.py
account/views.py
account/locale/ar/LC_MESSAGES/django.mo
account/locale/ar/LC_MESSAGES/django.po
account/locale/de/LC_MESSAGES/django.mo
account/locale/de/LC_MESSAGES/django.po
account/locale/es/LC_MESSAGES/django.mo
account/locale/es/LC_MESSAGES/django.po
account/locale/fa_IR/LC_MESSAGES/django.mo
account/locale/fa_IR/LC_MESSAGES/django.po
account/locale/fr/LC_MESSAGES/django.mo
account/locale/fr/LC_MESSAGES/django.po
account/locale/it/LC_MESSAGES/django.mo
account/locale/it/LC_MESSAGES/django.po
account/locale/ja/LC_MESSAGES/django.mo
account/locale/ja/LC_MESSAGES/django.po
account/locale/nl/LC_MESSAGES/django.mo
account/locale/nl/LC_MESSAGES/django.po
account/locale/pl/LC_MESSAGES/django.mo
account/locale/pl/LC_MESSAGES/django.po
account/locale/pt_BR/LC_MESSAGES/django.mo
account/locale/pt_BR/LC_MESSAGES/django.po
account/locale/ru/LC_MESSAGES/django.mo
account/locale/ru/LC_MESSAGES/django.po
account/locale/sk_SK/LC_MESSAGES/django.mo
account/locale/sk_SK/LC_MESSAGES/django.po
account/locale/tr/LC_MESSAGES/django.mo
account/locale/tr/LC_MESSAGES/django.po
account/locale/zh_CN/LC_MESSAGES/django.mo
account/locale/zh_CN/LC_MESSAGES/django.po
account/locale/zh_TW/LC_MESSAGES/django.mo
account/locale/zh_TW/LC_MESSAGES/django.po
account/management/__init__.py
account/management/commands/__init__.py
account/management/commands/expunge_deleted.py
account/management/commands/user_password_expiry.py
account/management/commands/user_password_history.py
account/migrations/0001_initial.py
account/migrations/0002_fix_str.py
geonode_user_accounts-1.0.15.dist-info/DESCRIPTION.rst
geonode_user_accounts-1.0.15.dist-info/METADATA
geonode_user_accounts-1.0.15.dist-info/RECORD
geonode_user_accounts-1.0.15.dist-info/WHEEL
geonode_user_accounts-1.0.15.dist-info/metadata.json
geonode_user_accounts-1.0.15.dist-info/top_level.txt
