Metadata-Version: 2.0
Name: geonode-user-accounts
Version: 1.0.15
Summary: a Django user account app
Home-page: https://github.com/GeoNode/geonode-user-accounts
Author: Brian Rosner
Author-email: brosner@gmail.com
License: MIT
Platform: UNKNOWN
Classifier: Development Status :: 5 - Production/Stable
Classifier: Environment :: Web Environment
Classifier: Intended Audience :: Developers
Classifier: License :: OSI Approved :: MIT License
Classifier: Operating System :: OS Independent
Classifier: Programming Language :: Python
Classifier: Programming Language :: Python :: 2
Classifier: Programming Language :: Python :: 3
Classifier: Framework :: Django
Requires-Dist: django-appconf (>=1.0.1)
Requires-Dist: pytz (>=2015.6)
